Metadata-Version: 2.1
Name: gradient-descent-edf1101
Version: 1.0
Summary: Gradient Descent module
Home-page: https://github.com/edf1101/GradientDescent
Author: Ed Fillingham
Classifier: Programming Language :: Python :: 3
Classifier: License :: OSI Approved :: MIT License
Classifier: Operating System :: OS Independent
Requires-Python: >=3.10
License-File: LICENSE
